{
  "dependencies": {
    "apis1": {
      "resourceId": "/subscriptions/[parameters('subscriptionId')]/resourceGroups/[parameters('resourceGroupName')]/providers/Microsoft.ApiManagement/service/EdmiBackend/apis/EdmiBackend",
      "type": "apis.azure"
    },
    "mssql1": {
      "resourceId": "/subscriptions/[parameters('subscriptionId')]/resourcegroups/[parameters('resourceGroupName')]/providers/Microsoft.Sql/servers/edmibackenddbserver/databases/Edmi_db",
      "type": "mssql.azure",
      "connectionId": "ConnectionStrings:DevConnection",
      "secretStore": "AzureAppSettings"
    }
  }
}